{"trial_id": "0025", "hyperparameters": {"space": [{"class_name": "Int", "config": {"name": "lstm_units", "default": null, "conditions": [], "min_value": 32, "max_value": 128, "step": 32, "sampling": "linear"}}, {"class_name": "Boolean", "config": {"name": "use_bidirectional", "default": false, "conditions": []}}, {"class_name": "Float", "config": {"name": "learning_rate", "default": 0.0001, "conditions": [], "min_value": 0.0001, "max_value": 0.01, "step": null, "sampling": "log"}}], "values": {"lstm_units": 32, "use_bidirectional": false, "learning_rate": 0.0037713086175852817, "tuner/epochs": 10, "tuner/initial_epoch": 0, "tuner/bracket": 0, "tuner/round": 0}}, "metrics": {"metrics": {"loss": {"direction": "min", "observations": [{"value": [0.4108718931674957], "step": 7}]}, "accuracy": {"direction": "max", "observations": [{"value": [0.8256250023841858], "step": 7}]}, "val_loss": {"direction": "min", "observations": [{"value": [0.41112545132637024], "step": 7}]}, "val_accuracy": {"direction": "max", "observations": [{"value": [0.8243749737739563], "step": 7}]}}}, "score": 0.8243749737739563, "best_step": 7, "status": "COMPLETED", "message": null}